{
  "routes": [
    {
      "method": "GET",
      "path": "/sponzori",
      "handler": "sponzori.find",
      "config": {
        "policies": []
      }
    },
    {
      "method": "GET",
      "path": "/sponzori/count",
      "handler": "sponzori.count",
      "config": {
        "policies": []
      }
    },
    {
      "method": "GET",
      "path": "/sponzori/:id",
      "handler": "sponzori.findOne",
      "config": {
        "policies": []
      }
    },
    {
      "method": "POST",
      "path": "/sponzori",
      "handler": "sponzori.create",
      "config": {
        "policies": []
      }
    },
    {
      "method": "PUT",
      "path": "/sponzori/:id",
      "handler": "sponzori.update",
      "config": {
        "policies": []
      }
    },
    {
      "method": "DELETE",
      "path": "/sponzori/:id",
      "handler": "sponzori.delete",
      "config": {
        "policies": []
      }
    }
  ]
}
